deluge_mcp/cli.py
deluge_mcp/main.py
deluge_mcp-0.2.4.dist-info/LICENSE
deluge_mcp-0.2.4.dist-info/METADATA
deluge_mcp-0.2.4.dist-info/WHEEL
deluge_mcp-0.2.4.dist-info/entry_points.txt
deluge_mcp-0.2.4.dist-info/RECORD
