Metadata-Version: 2.3
Name: deluge-mcp
Version: 0.2.4
Summary: Deluge torrent management via MCP protocol
Author: abi_jey
Author-email: git@public.abja.dev
Requires-Python: >=3.12, <4.0
Classifier: Programming Language :: Python :: 3
Classifier: Programming Language :: Python :: 3.12
Classifier: Programming Language :: Python :: 3.13
Requires-Dist: fastmcp (>=2.11.0)
Requires-Dist: typer (>=0.15.1)
